pyshot.py
webdriver_proxy.py
webelement_proxy.py
pyshot-0.0.2.dist-info/LICENSE
pyshot-0.0.2.dist-info/METADATA
pyshot-0.0.2.dist-info/WHEEL
pyshot-0.0.2.dist-info/entry_points.txt
pyshot-0.0.2.dist-info/top_level.txt
pyshot-0.0.2.dist-info/RECORD
