Metadata-Version: 2.1
Name: pyshot
Version: 0.0.2
Summary: Pytest plugin to facilitate screenshot taking with selenium webdriver
Home-page: https://github.com/anggelomos/pyshot
Author: anggelomos
Author-email: anggelomos@outlook.com
License: MIT License
Keywords: pytest,py.test,pyshot,screenshot,selenium,test,plugin
Platform: UNKNOWN
Classifier: Framework :: Pytest
Classifier: Programming Language :: Python :: 3
Classifier: Topic :: Software Development :: Testing
Classifier: Programming Language :: Python :: 3.8
Requires-Dist: pytest
Requires-Dist: selenium
